pybott/__init__.py
pybott/bott.py
pybott/spin_bott.py
pybott-2024.11.19.dist-info/METADATA
pybott-2024.11.19.dist-info/WHEEL
pybott-2024.11.19.dist-info/licenses/LICENSE.txt
pybott-2024.11.19.dist-info/RECORD
