Metadata-Version: 2.3
Name: PyBott
Version: 2024.11.19
Summary: This package computes the Bott index, a real space, disorder resistant, topological index.
Project-URL: Homepage, https://gitlab.com/starcluster/pybott
Project-URL: Documentation, https://pybott-1b2a5e.gitlab.io/index.html
Project-URL: Repository, https://gitlab.com/starcluster/pybott
Author-email: Pierre Wulles <pierre.wulles@lpmmc.cnrs.fr>
Maintainer-email: Pierre Wulles <pierre.wulles@lpmmc.cnrs.fr>
License:                     GNU GENERAL PUBLIC LICENSE
Keywords: chern,condensed,disordered,index,matter,number,photonic,tight-binding,topological
Classifier: Development Status :: 5 - Production/Stable
Classifier: Programming Language :: Python
Requires-Python: >=3.6
Requires-Dist: matplotlib
Requires-Dist: numpy
Requires-Dist: pandas
Requires-Dist: tqdm
